README.rst
setup.py
ioschedd/__init__.py
ioschedd/config.py
ioschedd/device.py
ioschedd/iosdaemon.py
ioschedd/service.py
ioschedd.egg-info/PKG-INFO
ioschedd.egg-info/SOURCES.txt
ioschedd.egg-info/dependency_links.txt
ioschedd.egg-info/entry_points.txt
ioschedd.egg-info/not-zip-safe
ioschedd.egg-info/requires.txt
ioschedd.egg-info/top_level.txt