Metadata-Version: 1.0
Name: ioschedd
Version: 0.1.1
Summary: Daemon to control per-device IO Scheduler             options in the Linux kernel
Home-page: http://github.com/fzylogic/ioschedd
Author: Jeremy Hanmer
Author-email: jeremy@dreamhost.com
License: Apache2
Platform: UNKNOWN
